{
    "id": "079",
    "Type": "Letter",
    "albumID": "005.003",
    "From": "Secretary, Kyathanahalli sahukar siddalingaiah virashiva samsaskruta pathashale",
    "To": "President, Kyathanahalli sahukar siddalingaiah virashiva samsaskruta pathashale",
    "Date": "12-07-1938",
    "Place": "ಮೈಸೂರು",
    "LanguagePresident, Kyathanahalli sahukar siddalingaiah virashiva samsaskruta pathashale": "kn",
    "Keywords": "Secretary, Kyathanahalli sahukar siddalingaiah virashiva samsaskruta pathashale, President, Kyathanahalli sahukar siddalingaiah virashiva samsaskruta pathashale"
}